treedlib/__init__.py
treedlib/features.py
treedlib/structs.py
treedlib/templates.py
treedlib/util.py
treedlib-0.1.3.dist-info/LICENSE
treedlib-0.1.3.dist-info/METADATA
treedlib-0.1.3.dist-info/WHEEL
treedlib-0.1.3.dist-info/top_level.txt
treedlib-0.1.3.dist-info/RECORD
