Metadata-Version: 2.1
Name: treedlib
Version: 0.1.3
Summary: Library of tree features.
Home-page: https://github.com/HazyResearch/treedlib
Author: Hazy Research
Author-email: UNKNOWN
License: UNKNOWN
Platform: UNKNOWN
Classifier: License :: OSI Approved :: MIT License
Requires-Dist: lxml
